aidge_quantization/aidge_quantization.cpython-311-x86_64-linux-gnu.so
aidge_quantization/__init__.py
aidge_quantization/onnx/qdq.py
aidge_quantization/onnx/__init__.py
aidge_quantization/onnx/qop.py
aidge_quantization.libs/libgomp-24e2ab19.so.1.0.0
aidge_quantization-0.5.0.dist-info/RECORD
aidge_quantization-0.5.0.dist-info/top_level.txt
aidge_quantization-0.5.0.dist-info/METADATA
aidge_quantization-0.5.0.dist-info/WHEEL
